des_process/__init__.py
des_process/processes.py
des_process/products.py
des_process/test_processes.py
des_process/test_products.py
des_process-1.5.0.dist-info/LICENSE
des_process-1.5.0.dist-info/METADATA
des_process-1.5.0.dist-info/WHEEL
des_process-1.5.0.dist-info/top_level.txt
des_process-1.5.0.dist-info/RECORD
